borg2mqtt/__init__.py
borg2mqtt/actions.py
borg2mqtt/const.py
borg2mqtt/repo.py
borg2mqtt-0.1.1.dist-info/LICENSE
borg2mqtt-0.1.1.dist-info/METADATA
borg2mqtt-0.1.1.dist-info/WHEEL
borg2mqtt-0.1.1.dist-info/entry_points.txt
borg2mqtt-0.1.1.dist-info/top_level.txt
borg2mqtt-0.1.1.dist-info/RECORD
