Metadata-Version: 2.1
Name: borg2mqtt
Version: 0.1.1
Summary: Send borg backup updates over MQTT
Author-email: Easton Potokar <contagon6@gmail.com>
Maintainer-email: Easton Potokar <contagon6@gmail.com>
Project-URL: Homepage, https://github.com/contagon/borg2mqtt
Project-URL: Bug Reports, https://github.com/contagon/borg2mqtt/issues
Project-URL: Source, https://github.com/contagon/borg2mqtt
Keywords: borg,mqtt,hass
Classifier: Development Status :: 4 - Beta
Classifier: Intended Audience :: Developers
Classifier: Topic :: Software Development :: Build Tools
Classifier: License :: OSI Approved :: MIT License
Classifier: Programming Language :: Python :: 3
Classifier: Programming Language :: Python :: 3.7
Classifier: Programming Language :: Python :: 3.8
Classifier: Programming Language :: Python :: 3.9
Classifier: Programming Language :: Python :: 3.10
Classifier: Programming Language :: Python :: 3.11
Classifier: Programming Language :: Python :: 3 :: Only
Requires-Python: >=3.7
License-File: LICENSE
Requires-Dist: paho-mqtt
Requires-Dist: platformdirs
Requires-Dist: python-slugify
Requires-Dist: pyyaml
Provides-Extra: dev
Requires-Dist: check-manifest ; extra == 'dev'
Requires-Dist: pre-commit ; extra == 'dev'
Provides-Extra: test
Requires-Dist: pytest ; extra == 'test'
